[
  {
    "type": "select",
    "label": "专场名称",
    "name": "projectId",
    "linkName": "scoreListStr",
    "data": [],
    "span": 12,
    "width": "130px",
    "filterable": true,
    "disabled": true
  },
  {
    "type": "textarea",
    "label": "备注",
    "name": "note",
    "span": 24,
    "width": "130px",
    "disabled": true
  },
  {
    "type": "inputTable",
    "label": "综合分评定规则",
    "name": "scoreListStr",
    "span": 24,
    "width": "130px",
    "useType": "use",
    "headers": [
      {
        "title": "打分项",
        "key": "itemName",
        "disabled": true
      },
      {
        "title": "评分标准",
        "key": "itemStandard",
        "disabled": true
      },
      {
        "title": "分值",
        "key": "itemScore",
        "disabled": true
      },
      {
        "title": "自评",
        "key": "selfScore",
        "disabled": true
      }
    ]
  },
  {
    "type": "image",
    "label": "综合分自评证明",
    "name": "viewfiles",
    "span": 24,
    "width": "130px"
  }
]